ocr_detection/__init__.py
ocr_detection/_analyzer.py
ocr_detection/_detector.py
ocr_detection/py.typed
ocr_detection/simple.py
ocr_detection-0.4.1.dist-info/WHEEL
ocr_detection-0.4.1.dist-info/METADATA
ocr_detection-0.4.1.dist-info/RECORD
