Metadata-Version: 2.3
Name: ocr-detection
Version: 0.4.1
Summary: A Python library to detect whether PDF pages contain extractable text or are scanned images requiring OCR
Keywords: pdf,ocr,text-extraction,document-processing,pdf-analysis
Author: satish
Author-email: satish <satish860@gmail.com>
License: MIT
Classifier: Development Status :: 4 - Beta
Classifier: Intended Audience :: Developers
Classifier: License :: OSI Approved :: MIT License
Classifier: Programming Language :: Python :: 3
Classifier: Programming Language :: Python :: 3.13
Classifier: Topic :: Software Development :: Libraries :: Python Modules
Classifier: Topic :: Text Processing :: General
Classifier: Topic :: Multimedia :: Graphics :: Graphics Conversion
Requires-Dist: pymupdf>=1.23.0
Requires-Dist: pdfplumber>=0.10.0
Maintainer: satish
Maintainer-email: satish <satish860@gmail.com>
Requires-Python: >=3.13
Project-URL: Documentation, https://github.com/satish860/ocr-detection#readme
Project-URL: Homepage, https://github.com/satish860/ocr-detection
Project-URL: Issues, https://github.com/satish860/ocr-detection/issues
Project-URL: Repository, https://github.com/satish860/ocr-detection
